yeastautoscore/__init__.py
yeastautoscore/__main__.py
yeastautoscore/gui/canvas.py
yeastautoscore/gui/panel.py
yeastautoscore/gui/window.py
yeastautoscore/io/file.py
yeastautoscore/io/folder.py
yeastautoscore/model/cnn.py
yeastautoscore/model/weights/conv_1_bias.npy
yeastautoscore/model/weights/conv_1_kernel.npy
yeastautoscore/model/weights/conv_2_bias.npy
yeastautoscore/model/weights/conv_2_kernel.npy
yeastautoscore/model/weights/conv_3_bias.npy
yeastautoscore/model/weights/conv_3_kernel.npy
yeastautoscore/model/weights/conv_4_bias.npy
yeastautoscore/model/weights/conv_4_kernel.npy
yeastautoscore/model/weights/conv_5_bias.npy
yeastautoscore/model/weights/conv_5_kernel.npy
yeastautoscore/model/weights/conv_6_bias.npy
yeastautoscore/model/weights/conv_6_kernel.npy
yeastautoscore/model/weights/conv_7_bias.npy
yeastautoscore/model/weights/conv_7_kernel.npy
yeastautoscore/model/weights/conv_8_kernel.npy
yeastautoscore/processing/draw.py
yeastautoscore/processing/grid.py
yeastautoscore-0.1.1.dist-info/METADATA
yeastautoscore-0.1.1.dist-info/WHEEL
yeastautoscore-0.1.1.dist-info/top_level.txt
yeastautoscore-0.1.1.dist-info/RECORD
