Metadata-Version: 2.4
Name: yeastautoscore
Version: 0.1.1
Summary: YeastAutoScore runs with python -m yeastautoscore
Author-email: "INET, Helmholtz Munich" <inet@helmholtz-munich.com>
Requires-Python: >=3.10
Requires-Dist: opencv-python<5.0,>=4.10
Requires-Dist: numpy>=2.2
